{
  "$id": "schemas/pf/route",
  "type": "object",
  "$meta": {
    "sql_processing": true,
    "sql_schema_name": "sipaf",
    "sql_table_name": "l_routes",
    "genre": "F",
    "label": "route",
    "geometry_field_name": "geom",
    "label_field_name": "route_name"
  },
  "properties": {
    "id_route": {
      "type": "integer",
      "label": "ID enfant",
      "primary_key": true
    },
    "route_name": {
      "label": "Code route",
      "type": "string"
    },
    "geom": {
      "label": "géometrie",
      "type": "geometry",
      "geometry_type": "geometry",
      "srid": 4326
    }
  }
}